Metadata-Version: 2.1
Name: dimsum
Version: 0.1.0
Summary: Relational operations built on GraphBLAS
Home-page: UNKNOWN
Author: Jim Kitchen and Erik Welch
License: UNKNOWN
Platform: UNKNOWN
Classifier: Programming Language :: Python :: 3 :: Only
Classifier: Operating System :: OS Independent
Classifier: Development Status :: 3 - Alpha
Classifier: License :: OSI Approved :: Apache Software License
Classifier: Topic :: Scientific/Engineering :: Information Analysis
Classifier: Topic :: Scientific/Engineering :: Mathematics
